speadi/__init__.py
speadi/common_tools/__init__.py
speadi/common_tools/check_acceleration.py
speadi/common_tools/check_inputs.py
speadi/common_tools/get_union.py
speadi/common_tools/result_arrays.py
speadi/common_tools/jax/__init__.py
speadi/common_tools/jax/jax_histogram.py
speadi/common_tools/jax/time_distance_matrix.py
speadi/common_tools/numba/__init__.py
speadi/common_tools/numba/numba_histogram.py
speadi/common_tools/numba/time_distance_matrix.py
speadi/common_tools/vectorized/__init__.py
speadi/common_tools/vectorized/time_distance_matrix.py
speadi/int_trrdf/__init__.py
speadi/int_trrdf/int_trrdf.py
speadi/int_trrdf/utils.py
speadi/int_trrdf/jax/__init__.py
speadi/int_trrdf/jax/add_distribution_function_time_slice.py
speadi/int_trrdf/jax/histogram_distances.py
speadi/int_trrdf/numba/__init__.py
speadi/int_trrdf/numba/add_distribution_function_time_slice.py
speadi/int_trrdf/numba/histogram_distances.py
speadi/int_trrdf/vectorized/__init__.py
speadi/int_trrdf/vectorized/add_distribution_function_time_slice.py
speadi/int_trrdf/vectorized/histogram_distances.py
speadi/time_resolved_rdf/__init__.py
speadi/time_resolved_rdf/trrdf.py
speadi/time_resolved_rdf/utils.py
speadi/time_resolved_rdf/jax/__init__.py
speadi/time_resolved_rdf/jax/add_distribution_function_time_slice.py
speadi/time_resolved_rdf/jax/histogram_distances.py
speadi/time_resolved_rdf/jit/__init__.py
speadi/time_resolved_rdf/jit/add_distribution_function_time_slice.py
speadi/time_resolved_rdf/jit/histogram_distances.py
speadi/time_resolved_rdf/jit/time_distance_matrix.py
speadi/time_resolved_rdf/numba/__init__.py
speadi/time_resolved_rdf/numba/add_distribution_function_time_slice.py
speadi/time_resolved_rdf/numba/histogram_distances.py
speadi/time_resolved_rdf/tools/__init__.py
speadi/time_resolved_rdf/tools/utils.py
speadi/time_resolved_rdf/vectorized/__init__.py
speadi/time_resolved_rdf/vectorized/add_distribution_function_time_slice.py
speadi/time_resolved_rdf/vectorized/histogram_distances.py
SPEADI-1.0.1.dist-info/AUTHORS
SPEADI-1.0.1.dist-info/LICENSE
SPEADI-1.0.1.dist-info/METADATA
SPEADI-1.0.1.dist-info/WHEEL
SPEADI-1.0.1.dist-info/top_level.txt
SPEADI-1.0.1.dist-info/RECORD
