Metadata-Version: 2.1
Name: SPEADI
Version: 1.0.1
Summary: A Python package that aims to characterise the dynamics of local chemical environments
Home-page: https://github.com/FZJ-JSC/speadi
Author: Emile de Bruyn
Author-email: e.de.bruyn@fz-juelich.de
Requires-Python: >=3.7
License-File: LICENSE
License-File: AUTHORS
Requires-Dist: importlib-metadata
Requires-Dist: requests
Requires-Dist: mdtraj >=1.5
Requires-Dist: numpy
Requires-Dist: matplotlib
Requires-Dist: tqdm
Provides-Extra: all
Requires-Dist: numpy >=1.21 ; extra == 'all'
Requires-Dist: numba ; extra == 'all'
Requires-Dist: jax ; extra == 'all'
Requires-Dist: jaxlib ; extra == 'all'
Requires-Dist: xarray ; extra == 'all'
Provides-Extra: jax
Requires-Dist: numpy >=1.21 ; extra == 'jax'
Requires-Dist: jax ; extra == 'jax'
Requires-Dist: jaxlib ; extra == 'jax'
Provides-Extra: numba
Requires-Dist: numpy >=1.21 ; extra == 'numba'
Requires-Dist: numba ; extra == 'numba'
